finec/__init__.py
finec/directory.py
finec/dividend.py
finec/moex.py
finec/ofdata.py
finec/yield_curve.py
finec-0.1.10.dist-info/LICENSE
finec-0.1.10.dist-info/WHEEL
finec-0.1.10.dist-info/METADATA
finec-0.1.10.dist-info/RECORD
