Metadata-Version: 2.1
Name: finec
Version: 0.1.10
Summary: Computational finance from Finec MGIMO
Author: Evgeniy Pogrebnyak
Author-email: e.pogrebnyak@gmail.com
Requires-Python: >=3.7.13,<4.0.0
Classifier: Programming Language :: Python :: 3
Classifier: Programming Language :: Python :: 3.8
Classifier: Programming Language :: Python :: 3.9
Requires-Dist: apimoex (>=1.2.0,<2.0.0)
Requires-Dist: appdirs (>=1.4.4,<2.0.0)
Requires-Dist: folium (>=0.2.1,<0.3.0)
Requires-Dist: httpx (>=0.22.0,<0.23.0)
Requires-Dist: lxml (>=4.9.1,<5.0.0)
Requires-Dist: matplotlib (>=3.5.2,<4.0.0)
Requires-Dist: pandas (==1.3.5)
Requires-Dist: pymongo (>=4.1.1,<5.0.0)
Requires-Dist: python-dotenv (>=0.20.0,<0.21.0)
Requires-Dist: requests (>=2.23.0,<3.0.0)
Requires-Dist: tqdm (>=4.64.0,<5.0.0)
